cloud_watch_logs/__init__.py
cloud_watch_logs/cloud_watch_logs.py
cloud_watch_logs/cloud_watch_logs_dto.py
cloud_watch_logs-1.0.1.dist-info/METADATA
cloud_watch_logs-1.0.1.dist-info/WHEEL
cloud_watch_logs-1.0.1.dist-info/top_level.txt
cloud_watch_logs-1.0.1.dist-info/RECORD
