Metadata-Version: 2.1
Name: cloud-watch-logs
Version: 1.0.1
Home-page: https://github.com/hwangyoungjae/cloud_watch_logs
Author: hwangyoungjae
Author-email: dudwo56@gmail.com
Project-URL: cloud_watch_logs, https://github.com/hwangyoungjae/cloud_watch_logs
Classifier: Programming Language :: Python :: 3
Classifier: License :: OSI Approved :: MIT License
Classifier: Operating System :: OS Independent
Requires-Python: >=3.8
Requires-Dist: boto3 (>=1.26.57)
Requires-Dist: lazy-streams (>=1.0.0)
Requires-Dist: promise-keeper (>=1.0.0)
Requires-Dist: python-dotenv (>=0.21.1)
